{"id":"counter6611","type":"counter","delta":55}
{"id":"gauge45","type":"gauge","value":24.5}
me5","type":"counter","delta":7456}
{"id":"Name4w","type":"counter","delta":-999999999}
{"id":"Name7w","type":"counter","delta":-1}
{"id":"Name1","type":"counter","delta":2}
{"id":"Name2","type":"counter","delta":0}
{"id":"Name2w","type":"counter","delta":1}
{"id":"Name3w","type":"counter","delta":999999999}
{"id":"Name6w","type":"counter","delta":7456}
{"id":"Name6","type":"counter","delta":-1}
{"id":"Name8w","type":"counter","delta":555}
{"id":"Name343","type":"counter","delta":555}
{"id":"AJcgl","type":"counter","delta":0}
{"id":"Name10w","type":"gauge","value":999999999.62}
{"id":"Name1","type":"gauge","value":1}
{"id":"Name2","type":"gauge","value":999999999.62}
{"id":"Name12w","type":"gauge","value":0}
{"id":"Name4","type":"gauge","value":0}
{"id":"Name14w","type":"gauge","value":-1}
{"id":"Name1w","type":"gauge","value":1}
{"id":"Name9w","type":"gauge","value":1}
{"id":"Name5","type":"gauge","value":7456.3231}
{"id":"Name15w","type":"gauge","value":555}
{"id":"Name13w","type":"gauge","value":7456.3231}
{"id":"Name11w","type":"gauge","value":-999999999.38}
{"id":"Name3","type":"gauge","value":-999999999.38}
:"gauge","value":0}
{"id":"Name9w","type":"gauge","value":1}
{"id":"Name10w","type":"gauge","value":999999999.62}
{"id":"Name11w","type":"gauge","value":-999999999.38}
{"id":"Name12w","type":"gauge","value":0}
{"id":"dVise","type":"gauge","value":0}
{"id":"Name343","type":"gauge","value":555}
{"id":"gauge45","type":"gauge","value":24.5}
{"id":"Name2","type":"gauge","value":999999999.62}
{"id":"Name14w","type":"gauge","value":-1}
{"id":"DzdXa","type":"gauge","value":0}
{"id":"oOKwQ","type":"gauge","value":0}
{"id":"bDDqm","type":"gauge","value":0}
{"id":"mcpSM","type":"gauge","value":0}
{"id":"Name6","type":"gauge","value":-1}
{"id":"Name1w","type":"gauge","value":1}
{"id":"Name1","type":"gauge","value":1}
{"id":"Name13w","type":"gauge","value":7456.3231}
{"id":"Name15w","type":"gauge","value":555}
{"id":"Name4","type":"gauge","value":0}
{"id":"Yigij","type":"gauge","value":0}
{"id":"eAzUs","type":"gauge","value":0}
